Workbook

Sheet 🏠 Portada
B2: CALCULADORA DE PRECIOS
B4: Herramienta para fijar el precio justo de tus servicios y productos
B6: DATOS DE TU NEGOCIO
B7: Nombre del negocio / freelancer | C7: Tu Nombre o Empresa
B8: Sector | C8: Ej: Consultoría, Formación, Ingeniería…
B9: Moneda | C9: EUR
B10: IVA general aplicable (%) | C10: 21
B11: Fecha de actualización | C11: 09/06/2026
B13: PESTAÑAS DISPONIBLES
B14: 👥 Equipo | C14: Define tu equipo, tarifas y capacidad facturable mensual.
B15: 📚 Formaciones | C15: Calcula el precio de cursos, talleres y formaciones.
B16: 🤝 Consultoría | C16: Proyectos de consultoría estratégica y asesoramiento.
B17: ⚙️ Ingeniería | C17: Proyectos técnicos, desarrollo e implementación.
B18: 📦 Producto | C18: Productos físicos o digitales con margen comercial.
B19: 📊 Resumen | C19: Comparativa de precios de todas las categorías.
B21: LEYENDA DE COLORES
B22: ■ Ejemplo | C22: Celda de entrada → Escribe tu dato aquí
B23: ■ Ejemplo | C23: Fórmula calculada → No modificar
B24: ■ Ejemplo | C24: Precio recomendado → Resultado final
B25: ■ Ejemplo | C25: Dato clave → Requiere revisión
B27: Fórmula: Precio = Coste Total + Margen + Prima de Valor

Sheet 👥 Equipo
B1: EQUIPO — CAPACIDAD Y COSTES
B4: Las horas facturables totales del equipo se usan automáticamente en todas las pestañas de servicio para prorratear los costes indirectos.
B6: Nombre / Rol | C6: Tipo | D6: Horas contratadas/mes | E6: % Tiempo facturable | F6: Horas facturables/mes | G6: Coste mensual (€)
C7: Propio/Colaborador | D7: h/mes | E7: % | F7: D × E | G7: €/mes
B8: Persona 1 | C8: Propio | D8: 160 | E8: 0.75 | F8: =D8*E8 -> 120 | G8: 0
B9: Persona 2 | C9: Propio | D9: 160 | E9: 0.75 | F9: =D9*E9 -> 120 | G9: 0
B10: Persona 3 | C10: Propio | D10: 160 | E10: 0.75 | F10: =D10*E10 -> 120 | G10: 0
B11: Persona 4 | C11: Propio | D11: 160 | E11: 0.75 | F11: =D11*E11 -> 120 | G11: 0
B12: Persona 5 | C12: Propio | D12: 160 | E12: 0.75 | F12: =D12*E12 -> 120 | G12: 0
B13: Persona 6 | C13: Propio | D13: 160 | E13: 0.75 | F13: =D13*E13 -> 120 | G13: 0
B14: Persona 7 | C14: Propio | D14: 160 | E14: 0.75 | F14: =D14*E14 -> 120 | G14: 0
B15: Persona 8 | C15: Propio | D15: 160 | E15: 0.75 | F15: =D15*E15 -> 120 | G15: 0
B17: TOTALES DEL EQUIPO | F17: =SUM(F8:F15) -> 960 | G17: =SUM(G8:G15) -> 0
B19: VALORES USADOS EN LAS CALCULADORAS
B20: Horas facturables totales/mes (equipo) | F20: =F17 -> 960 | G20: h/mes
B21: Coste total mensual del equipo (nóminas) | F21: =G17 -> 0 | G21: €/mes

Sheet 📚 Formaciones
B1: CALCULADORA DE PRECIOS — FORMACIONES
B4: A. COSTES DIRECTOS
B5: Personal propio (horas en este proyecto)
B6: Horas de trabajo propias | C6: 10 | D6: h
B7: Tarifa hora propia (referencia) | C7: 50 | D7: €/h
B8: Subtotal personal propio | D8: € | E8: =C6*C7 -> 500
B9: Colaboradores / Proveedores externos (hasta 5)
B10: Colaborador 1 — horas | C10: 0 | D10: h
B11: Colaborador 1 — tarifa/hora | C11: 0 | D11: €/h
B12: Subtotal colaborador 1 | E12: =C10*C11 -> 0
B13: Colaborador 2 — horas | C13: 0 | D13: h
B14: Colaborador 2 — tarifa/hora | C14: 0 | D14: €/h
B15: Subtotal colaborador 2 | E15: =C13*C14 -> 0
B16: Colaborador 3 — horas | C16: 0 | D16: h
B17: Colaborador 3 — tarifa/hora | C17: 0 | D17: €/h
B18: Subtotal colaborador 3 | E18: =C16*C17 -> 0
B19: Colaborador 4 — horas | C19: 0 | D19: h
B20: Colaborador 4 — tarifa/hora | C20: 0 | D20: €/h
B21: Subtotal colaborador 4 | E21: =C19*C20 -> 0
B22: Colaborador 5 — horas | C22: 0 | D22: h
B23: Colaborador 5 — tarifa/hora | C23: 0 | D23: €/h
B24: Subtotal colaborador 5 | E24: =C22*C23 -> 0
B25: Subtotal colaboradores (todos) | D25: € | E25: =E12+E15+E18+E21+E24 -> 0
B26: Otros costes directos
B27: Herramientas y software | C27: 0 | D27: €
B28: Materiales / entregables | C28: 0 | D28: €
B29: Desplazamientos y dietas | C29: 0 | D29: €
B30: Sala / plataforma de formación | C30: 0 | D30: €
B31: Materiales pedagógicos / manuales | C31: 0 | D31: €
B32: TOTAL COSTES DIRECTOS (A) | D32: € | E32: =E8+E25+E27+E28+E29+E30+E31 -> 500
B34: B. COSTES INDIRECTOS (estructura mensual prorrateada)
B35: Nóminas y costes de personal fijo (desde pestaña Equipo) | D35: €/mes | E35: ='👥 Equipo'!G17 -> 0
B36: Alquiler y suministros | C36: 0 | D36: €/mes
B37: Seguros | C37: 0 | D37: €/mes
B38: Cuota autónomos / costes societarios | C38: 0 | D38: €/mes
B39: Contabilidad y asesoría | C39: 0 | D39: €/mes
B40: Marketing y publicidad | C40: 0 | D40: €/mes
B41: Formación y desarrollo profesional | C41: 0 | D41: €/mes
B42: Herramientas de gestión | C42: 0 | D42: €/mes
B43: Total indirectos/mes (sin nóminas) | D43: € | E43: =SUM(C36:C42) -> 0
B44: Total indirectos/mes (con nóminas) | D44: € | E44: =E43+E35 -> 0
B45: Horas facturables totales/mes (desde pestaña Equipo) | D45: h/mes | E45: ='👥 Equipo'!F17 -> 960
B46: Horas totales dedicadas a este proyecto | C46: 10 | D46: h
B47: TOTAL COSTES INDIRECTOS IMPUTADOS (B) | D47: € | E47: =IF(E45=0,0,E44/E45*C46) -> 0
B49: C. TIEMPO NO FACTURABLE (coste oportunidad)
B50: Preparación | C50: 0 | D50: h
B51: Reuniones comerciales | C51: 0 | D51: h
B52: Administración | C52: 0 | D52: h
B53: Seguimiento post-entrega | C53: 0 | D53: h
B54: Atención al cliente | C54: 0 | D54: h
B55: Diseño y mejora de procesos | C55: 0 | D55: h
B56: Total horas no facturables | D56: h | E56: =SUM(C50:C55) -> 0
B57: COSTE TIEMPO NO FACTURABLE (C) | D57: € | E57: =E56*C7 -> 0
B59: COSTE BASE TOTAL (A+B+C) | D59: € | E59: =E32+E47+E57 -> 500
B61: D. MARGEN DE BENEFICIO DESEADO
B62: Margen mínimo (%) | C62: 0.15 | D62: %
B63: Margen objetivo (%) | C63: 0.3 | D63: %
B64: Reserva para reinversión (%) | C64: 0.05 | D64: %
B65: Margen total aplicado (%) | D65: % | E65: =C63+C64 -> 0.35
B66: Precio con coste + margen | D66: € | E66: =IF((1-E65)=0,0,E59/(1-E65)) -> 769.23077
B68: E. VALOR APORTADO AL CLIENTE
B69: Evalúa del 1 (bajo) al 5 (muy alto). El factor ajusta el precio según el impacto generado.
B70: Problema crítico que resuelve (1-5) | C70: 3 | D70: 1-5
B71: Impacto económico generado (1-5) | C71: 3 | D71: 1-5
B72: Ahorro de tiempo del cliente (1-5) | C72: 3 | D72: 1-5
B73: Reducción de riesgos (1-5) | C73: 3 | D73: 1-5
B74: Transformación / resultado obtenido (1-5) | C74: 3 | D74: 1-5
B75: Nivel de especialización requerido (1-5) | C75: 3 | D75: 1-5
B76: Puntuación media de valor | D76: /5 | E76: =AVERAGE(C70:C75) -> 3
B77: Factor de valor (1.00 – 1.50) | D77: x | E77: =1+(E76-1)*0.5/4 -> 1.25
B79: F. POSICIONAMIENTO DE MARCA
B80: Posicionamiento (1=Accesible / 2=Intermedio / 3=Premium) | C80: 2 | D80: 1-3
B81: Factor posicionamiento (0.85 – 1.20) | D81: x | E81: =0.85+(E80-1)*0.175 -> 0.675
B83: G. MERCADO Y COMPETENCIA
B84: Precio referencia competidor 1 | C84: 0 | D84: €
B85: Precio referencia competidor 2 | C85: 0 | D85: €
B86: Precio referencia competidor 3 | C86: 0 | D86: €
B87: Disposición a pagar del cliente ideal | C87: 0 | D87: €
B88: Media precios de mercado | D88: € | E88: =IFERROR(AVERAGEIF(C84:C86,">0"),0) -> 0
B90: H. RIESGO Y COMPLEJIDAD
B91: Grado de personalización (1-5) | C91: 3 | D91: 1-5
B92: Responsabilidad asumida (1-5) | C92: 3 | D92: 1-5
B93: Urgencia (1-5) | C93: 3 | D93: 1-5
B94: Incertidumbre del proyecto (1-5) | C94: 3 | D94: 1-5
B95: Puntuación media de riesgo | D95: /5 | E95: =AVERAGE(C91:C94) -> 3
B96: Prima de riesgo (0% – 20%) | D96: % | E96: =(E95-1)*0.05 -> 0.1
B98: I. FORMATO DE PRESTACIÓN
B99: Formato (1=Hora / 2=Sesión / 3=Proyecto / 4=Retainer / 5=Grupal) | C99: 3 | D99: 1-5
B100: Nº de participantes / unidades (si aplica) | C100: 1 | D100: uds
B102: 📊 RESUMEN DE CÁLCULO
B103: ① Precio base (coste + margen) | D103: € | E103: =E66 -> 769.23077
B104: ② Ajuste por valor aportado | D104: € | E104: =E103*E77 -> 961.53846
B105: ③ Ajuste por posicionamiento | D105: € | E105: =E104*E81 -> 649.03846
B106: ④ Prima de riesgo (€) | D106: € | E106: =E105*E96 -> 64.903846
B107: ⑤ PRECIO RECOMENDADO (sin IVA) | D107: € | E107: =E105+E106 -> 713.94231
B108: ⑥ IVA (desde Portada) | D108: % | E108: ='🏠 Portada'!C10/100 -> 0.21
B109: IVA en € | D109: € | E109: =E107*E108 -> 149.92788
B110: 💰 PRECIO FINAL AL CLIENTE (con IVA) | E110: =E107+E109 -> 863.87019
B112: Precio por participante / unidad | D112: € | E112: =IF(C100>1,E110/C100,E110) -> 863.87019
B113: Precio mínimo aceptable (margen mínimo) | D113: € | E113: =IF((1-C62-C64)=0,0,E59/(1-C62-C64)*(1+E108)) -> 756.25
...

Sheet 🤝 Consultoría
B1: CALCULADORA DE PRECIOS — CONSULTORÍA
B4: A. COSTES DIRECTOS
B5: Personal propio (horas en este proyecto)
B6: Horas de trabajo propias | C6: 10 | D6: h
B7: Tarifa hora propia (referencia) | C7: 50 | D7: €/h
B8: Subtotal personal propio | D8: € | E8: =C6*C7 -> 500
B9: Colaboradores / Proveedores externos (hasta 5)
B10: Colaborador 1 — horas | C10: 0 | D10: h
B11: Colaborador 1 — tarifa/hora | C11: 0 | D11: €/h
B12: Subtotal colaborador 1 | E12: =C10*C11 -> 0
B13: Colaborador 2 — horas | C13: 0 | D13: h
B14: Colaborador 2 — tarifa/hora | C14: 0 | D14: €/h
B15: Subtotal colaborador 2 | E15: =C13*C14 -> 0
B16: Colaborador 3 — horas | C16: 0 | D16: h
B17: Colaborador 3 — tarifa/hora | C17: 0 | D17: €/h
B18: Subtotal colaborador 3 | E18: =C16*C17 -> 0
B19: Colaborador 4 — horas | C19: 0 | D19: h
B20: Colaborador 4 — tarifa/hora | C20: 0 | D20: €/h
B21: Subtotal colaborador 4 | E21: =C19*C20 -> 0
B22: Colaborador 5 — horas | C22: 0 | D22: h
B23: Colaborador 5 — tarifa/hora | C23: 0 | D23: €/h
B24: Subtotal colaborador 5 | E24: =C22*C23 -> 0
B25: Subtotal colaboradores (todos) | D25: € | E25: =E12+E15+E18+E21+E24 -> 0
B26: Otros costes directos
B27: Herramientas y software | C27: 0 | D27: €
B28: Materiales / entregables | C28: 0 | D28: €
B29: Desplazamientos y dietas | C29: 0 | D29: €
B30: Informes y documentación especializada | C30: 0 | D30: €
B31: Software de análisis / BI | C31: 0 | D31: €
B32: TOTAL COSTES DIRECTOS (A) | D32: € | E32: =E8+E25+E27+E28+E29+E30+E31 -> 500
B34: B. COSTES INDIRECTOS (estructura mensual prorrateada)
B35: Nóminas y costes de personal fijo (desde pestaña Equipo) | D35: €/mes | E35: ='👥 Equipo'!G17 -> 0
B36: Alquiler y suministros | C36: 0 | D36: €/mes
B37: Seguros | C37: 0 | D37: €/mes
B38: Cuota autónomos / costes societarios | C38: 0 | D38: €/mes
B39: Contabilidad y asesoría | C39: 0 | D39: €/mes
B40: Marketing y publicidad | C40: 0 | D40: €/mes
B41: Formación y desarrollo profesional | C41: 0 | D41: €/mes
B42: Herramientas de gestión | C42: 0 | D42: €/mes
B43: Total indirectos/mes (sin nóminas) | D43: € | E43: =SUM(C36:C42) -> 0
B44: Total indirectos/mes (con nóminas) | D44: € | E44: =E43+E35 -> 0
B45: Horas facturables totales/mes (desde pestaña Equipo) | D45: h/mes | E45: ='👥 Equipo'!F17 -> 960
B46: Horas totales dedicadas a este proyecto | C46: 10 | D46: h
B47: TOTAL COSTES INDIRECTOS IMPUTADOS (B) | D47: € | E47: =IF(E45=0,0,E44/E45*C46) -> 0
B49: C. TIEMPO NO FACTURABLE (coste oportunidad)
B50: Preparación | C50: 0 | D50: h
B51: Reuniones comerciales | C51: 0 | D51: h
B52: Administración | C52: 0 | D52: h
B53: Seguimiento post-entrega | C53: 0 | D53: h
B54: Atención al cliente | C54: 0 | D54: h
B55: Diseño y mejora de procesos | C55: 0 | D55: h
B56: Total horas no facturables | D56: h | E56: =SUM(C50:C55) -> 0
B57: COSTE TIEMPO NO FACTURABLE (C) | D57: € | E57: =E56*C7 -> 0
B59: COSTE BASE TOTAL (A+B+C) | D59: € | E59: =E32+E47+E57 -> 500
B61: D. MARGEN DE BENEFICIO DESEADO
B62: Margen mínimo (%) | C62: 0.15 | D62: %
B63: Margen objetivo (%) | C63: 0.3 | D63: %
B64: Reserva para reinversión (%) | C64: 0.05 | D64: %
B65: Margen total aplicado (%) | D65: % | E65: =C63+C64 -> 0.35
B66: Precio con coste + margen | D66: € | E66: =IF((1-E65)=0,0,E59/(1-E65)) -> 769.23077
B68: E. VALOR APORTADO AL CLIENTE
B69: Evalúa del 1 (bajo) al 5 (muy alto). El factor ajusta el precio según el impacto generado.
B70: Problema crítico que resuelve (1-5) | C70: 3 | D70: 1-5
B71: Impacto económico generado (1-5) | C71: 3 | D71: 1-5
B72: Ahorro de tiempo del cliente (1-5) | C72: 3 | D72: 1-5
B73: Reducción de riesgos (1-5) | C73: 3 | D73: 1-5
B74: Transformación / resultado obtenido (1-5) | C74: 3 | D74: 1-5
B75: Nivel de especialización requerido (1-5) | C75: 3 | D75: 1-5
B76: Puntuación media de valor | D76: /5 | E76: =AVERAGE(C70:C75) -> 3
B77: Factor de valor (1.00 – 1.50) | D77: x | E77: =1+(E76-1)*0.5/4 -> 1.25
B79: F. POSICIONAMIENTO DE MARCA
B80: Posicionamiento (1=Accesible / 2=Intermedio / 3=Premium) | C80: 2 | D80: 1-3
B81: Factor posicionamiento (0.85 – 1.20) | D81: x | E81: =0.85+(E80-1)*0.175 -> 0.675
B83: G. MERCADO Y COMPETENCIA
B84: Precio referencia competidor 1 | C84: 0 | D84: €
B85: Precio referencia competidor 2 | C85: 0 | D85: €
B86: Precio referencia competidor 3 | C86: 0 | D86: €
B87: Disposición a pagar del cliente ideal | C87: 0 | D87: €
B88: Media precios de mercado | D88: € | E88: =IFERROR(AVERAGEIF(C84:C86,">0"),0) -> 0
B90: H. RIESGO Y COMPLEJIDAD
B91: Grado de personalización (1-5) | C91: 3 | D91: 1-5
B92: Responsabilidad asumida (1-5) | C92: 3 | D92: 1-5
B93: Urgencia (1-5) | C93: 3 | D93: 1-5
B94: Incertidumbre del proyecto (1-5) | C94: 3 | D94: 1-5
B95: Puntuación media de riesgo | D95: /5 | E95: =AVERAGE(C91:C94) -> 3
B96: Prima de riesgo (0% – 20%) | D96: % | E96: =(E95-1)*0.05 -> 0.1
B98: I. FORMATO DE PRESTACIÓN
B99: Formato (1=Hora / 2=Sesión / 3=Proyecto / 4=Retainer / 5=Grupal) | C99: 3 | D99: 1-5
B100: Nº de participantes / unidades (si aplica) | C100: 1 | D100: uds
B102: 📊 RESUMEN DE CÁLCULO
B103: ① Precio base (coste + margen) | D103: € | E103: =E66 -> 769.23077
B104: ② Ajuste por valor aportado | D104: € | E104: =E103*E77 -> 961.53846
B105: ③ Ajuste por posicionamiento | D105: € | E105: =E104*E81 -> 649.03846
B106: ④ Prima de riesgo (€) | D106: € | E106: =E105*E96 -> 64.903846
B107: ⑤ PRECIO RECOMENDADO (sin IVA) | D107: € | E107: =E105+E106 -> 713.94231
B108: ⑥ IVA (desde Portada) | D108: % | E108: ='🏠 Portada'!C10/100 -> 0.21
B109: IVA en € | D109: € | E109: =E107*E108 -> 149.92788
B110: 💰 PRECIO FINAL AL CLIENTE (con IVA) | E110: =E107+E109 -> 863.87019
B112: Precio por participante / unidad | D112: € | E112: =IF(C100>1,E110/C100,E110) -> 863.87019
B113: Precio mínimo aceptable (margen mínimo) | D113: € | E113: =IF((1-C62-C64)=0,0,E59/(1-C62-C64)*(1+E108)) -> 756.25
...

Sheet ⚙️ Ingeniería
B1: CALCULADORA DE PRECIOS — INGENIERÍA
B4: A. COSTES DIRECTOS
B5: Personal propio (horas en este proyecto)
B6: Horas de trabajo propias | C6: 10 | D6: h
B7: Tarifa hora propia (referencia) | C7: 50 | D7: €/h
B8: Subtotal personal propio | D8: € | E8: =C6*C7 -> 500
B9: Colaboradores / Proveedores externos (hasta 5)
B10: Colaborador 1 — horas | C10: 0 | D10: h
B11: Colaborador 1 — tarifa/hora | C11: 0 | D11: €/h
B12: Subtotal colaborador 1 | E12: =C10*C11 -> 0
B13: Colaborador 2 — horas | C13: 0 | D13: h
B14: Colaborador 2 — tarifa/hora | C14: 0 | D14: €/h
B15: Subtotal colaborador 2 | E15: =C13*C14 -> 0
B16: Colaborador 3 — horas | C16: 0 | D16: h
B17: Colaborador 3 — tarifa/hora | C17: 0 | D17: €/h
B18: Subtotal colaborador 3 | E18: =C16*C17 -> 0
B19: Colaborador 4 — horas | C19: 0 | D19: h
B20: Colaborador 4 — tarifa/hora | C20: 0 | D20: €/h
B21: Subtotal colaborador 4 | E21: =C19*C20 -> 0
B22: Colaborador 5 — horas | C22: 0 | D22: h
B23: Colaborador 5 — tarifa/hora | C23: 0 | D23: €/h
B24: Subtotal colaborador 5 | E24: =C22*C23 -> 0
B25: Subtotal colaboradores (todos) | D25: € | E25: =E12+E15+E18+E21+E24 -> 0
B26: Otros costes directos
B27: Herramientas y software | C27: 0 | D27: €
B28: Materiales / entregables | C28: 0 | D28: €
B29: Desplazamientos y dietas | C29: 0 | D29: €
B30: Licencias técnicas (CAD, BIM, etc.) | C30: 0 | D30: €
B31: Prototipado y pruebas | C31: 0 | D31: €
B32: Subcontratación especializada | C32: 0 | D32: €
B33: TOTAL COSTES DIRECTOS (A) | D33: € | E33: =E8+E25+E27+E28+E29+E30+E31+E32 -> 500
B35: B. COSTES INDIRECTOS (estructura mensual prorrateada)
B36: Nóminas y costes de personal fijo (desde pestaña Equipo) | D36: €/mes | E36: ='👥 Equipo'!G17 -> 0
B37: Alquiler y suministros | C37: 0 | D37: €/mes
B38: Seguros | C38: 0 | D38: €/mes
B39: Cuota autónomos / costes societarios | C39: 0 | D39: €/mes
B40: Contabilidad y asesoría | C40: 0 | D40: €/mes
B41: Marketing y publicidad | C41: 0 | D41: €/mes
B42: Formación y desarrollo profesional | C42: 0 | D42: €/mes
B43: Herramientas de gestión | C43: 0 | D43: €/mes
B44: Total indirectos/mes (sin nóminas) | D44: € | E44: =SUM(C37:C43) -> 0
B45: Total indirectos/mes (con nóminas) | D45: € | E45: =E44+E36 -> 0
B46: Horas facturables totales/mes (desde pestaña Equipo) | D46: h/mes | E46: ='👥 Equipo'!F17 -> 960
B47: Horas totales dedicadas a este proyecto | C47: 10 | D47: h
B48: TOTAL COSTES INDIRECTOS IMPUTADOS (B) | D48: € | E48: =IF(E46=0,0,E45/E46*C47) -> 0
B50: C. TIEMPO NO FACTURABLE (coste oportunidad)
B51: Preparación | C51: 0 | D51: h
B52: Reuniones comerciales | C52: 0 | D52: h
B53: Administración | C53: 0 | D53: h
B54: Seguimiento post-entrega | C54: 0 | D54: h
B55: Atención al cliente | C55: 0 | D55: h
B56: Diseño y mejora de procesos | C56: 0 | D56: h
B57: Total horas no facturables | D57: h | E57: =SUM(C51:C56) -> 0
B58: COSTE TIEMPO NO FACTURABLE (C) | D58: € | E58: =E57*C7 -> 0
B60: COSTE BASE TOTAL (A+B+C) | D60: € | E60: =E33+E48+E58 -> 500
B62: D. MARGEN DE BENEFICIO DESEADO
B63: Margen mínimo (%) | C63: 0.15 | D63: %
B64: Margen objetivo (%) | C64: 0.3 | D64: %
B65: Reserva para reinversión (%) | C65: 0.05 | D65: %
B66: Margen total aplicado (%) | D66: % | E66: =C64+C65 -> 0.35
B67: Precio con coste + margen | D67: € | E67: =IF((1-E66)=0,0,E60/(1-E66)) -> 769.23077
B69: E. VALOR APORTADO AL CLIENTE
B70: Evalúa del 1 (bajo) al 5 (muy alto). El factor ajusta el precio según el impacto generado.
B71: Problema crítico que resuelve (1-5) | C71: 3 | D71: 1-5
B72: Impacto económico generado (1-5) | C72: 3 | D72: 1-5
B73: Ahorro de tiempo del cliente (1-5) | C73: 3 | D73: 1-5
B74: Reducción de riesgos (1-5) | C74: 3 | D74: 1-5
B75: Transformación / resultado obtenido (1-5) | C75: 3 | D75: 1-5
B76: Nivel de especialización requerido (1-5) | C76: 3 | D76: 1-5
B77: Puntuación media de valor | D77: /5 | E77: =AVERAGE(C71:C76) -> 3
B78: Factor de valor (1.00 – 1.50) | D78: x | E78: =1+(E77-1)*0.5/4 -> 1.25
B80: F. POSICIONAMIENTO DE MARCA
B81: Posicionamiento (1=Accesible / 2=Intermedio / 3=Premium) | C81: 2 | D81: 1-3
B82: Factor posicionamiento (0.85 – 1.20) | D82: x | E82: =0.85+(E81-1)*0.175 -> 0.675
B84: G. MERCADO Y COMPETENCIA
B85: Precio referencia competidor 1 | C85: 0 | D85: €
B86: Precio referencia competidor 2 | C86: 0 | D86: €
B87: Precio referencia competidor 3 | C87: 0 | D87: €
B88: Disposición a pagar del cliente ideal | C88: 0 | D88: €
B89: Media precios de mercado | D89: € | E89: =IFERROR(AVERAGEIF(C85:C87,">0"),0) -> 0
B91: H. RIESGO Y COMPLEJIDAD
B92: Grado de personalización (1-5) | C92: 3 | D92: 1-5
B93: Responsabilidad asumida (1-5) | C93: 3 | D93: 1-5
B94: Urgencia (1-5) | C94: 3 | D94: 1-5
B95: Incertidumbre del proyecto (1-5) | C95: 3 | D95: 1-5
B96: Puntuación media de riesgo | D96: /5 | E96: =AVERAGE(C92:C95) -> 3
B97: Prima de riesgo (0% – 20%) | D97: % | E97: =(E96-1)*0.05 -> 0.1
B99: I. FORMATO DE PRESTACIÓN
B100: Formato (1=Hora / 2=Sesión / 3=Proyecto / 4=Retainer / 5=Grupal) | C100: 3 | D100: 1-5
B101: Nº de participantes / unidades (si aplica) | C101: 1 | D101: uds
B103: 📊 RESUMEN DE CÁLCULO
B104: ① Precio base (coste + margen) | D104: € | E104: =E67 -> 769.23077
B105: ② Ajuste por valor aportado | D105: € | E105: =E104*E78 -> 961.53846
B106: ③ Ajuste por posicionamiento | D106: € | E106: =E105*E82 -> 649.03846
B107: ④ Prima de riesgo (€) | D107: € | E107: =E106*E97 -> 64.903846
B108: ⑤ PRECIO RECOMENDADO (sin IVA) | D108: € | E108: =E106+E107 -> 713.94231
B109: ⑥ IVA (desde Portada) | D109: % | E109: ='🏠 Portada'!C10/100 -> 0.21
B110: IVA en € | D110: € | E110: =E108*E109 -> 149.92788
B111: 💰 PRECIO FINAL AL CLIENTE (con IVA) | E111: =E108+E110 -> 863.87019
B113: Precio por participante / unidad | D113: € | E113: =IF(C101>1,E111/C101,E111) -> 863.87019
...

Sheet 📦 Producto
B1: CALCULADORA DE PRECIOS — PRODUCTO
B4: A. COSTE DE ADQUISICIÓN O FABRICACIÓN (por unidad)
B5: Materias primas | C5: 0 | D5: €/ud
B6: Producción / fabricación | C6: 0 | D6: €/ud
B7: Mano de obra directa | C7: 0 | D7: €/ud
B8: Empaquetado | C8: 0 | D8: €/ud
B9: Etiquetado | C9: 0 | D9: €/ud
B10: TOTAL FABRICACIÓN (A) | D10: € | E10: =SUM(C5:C9) -> 0
B12: B. COSTES LOGÍSTICOS (por unidad)
B13: Almacenamiento | C13: 0 | D13: €/ud
B14: Transporte | C14: 0 | D14: €/ud
B15: Envíos | C15: 0 | D15: €/ud
B16: Devoluciones (estimado) | C16: 0 | D16: €/ud
B17: TOTAL LOGÍSTICA (B) | D17: € | E17: =SUM(C13:C16) -> 0
B19: C. COSTES INDIRECTOS (prorrateo mensual)
B20: Marketing y publicidad | C20: 0 | D20: €/mes
B21: Personal | C21: 0 | D21: €/mes
B22: Software y herramientas | C22: 0 | D22: €/mes
B23: Administración y gestoría | C23: 0 | D23: €/mes
B24: Alquileres y suministros | C24: 0 | D24: €/mes
B25: Unidades vendidas al mes (estimado) | C25: 100 | D25: uds/mes
B26: Total indirectos/mes | D26: € | E26: =SUM(C20:C24) -> 0
B27: TOTAL INDIRECTOS POR UNIDAD (C) | D27: € | E27: =IF(C25=0,0,E26/C25) -> 0
B29: D. IMPUESTOS
B30: IVA/VAT (%) | C30: 0.21 | D30: %
B31: Aranceles (si procede) (%) | C31: 0 | D31: %
B33: COSTE TOTAL UNITARIO (A+B+C) | D33: € | E33: =E10+E17+E27 -> 0
B35: E. MARGEN COMERCIAL DESEADO
B36: Margen bruto objetivo (%) | C36: 0.4 | D36: %
B37: Margen neto objetivo (%) | C37: 0.2 | D37: %
B38: Fondo para reinversión (%) | C38: 0.05 | D38: %
B39: Margen total aplicado (%) | D39: % | E39: =C36+C38 -> 0.45
B40: PVP sin IVA (coste + margen) | D40: € | E40: =IF((1-E39)=0,0,E33/(1-E39)) -> 0
B42: F. VALOR PERCIBIDO
B43: Evalúa del 1 (bajo) al 5 (muy alto) cada atributo de valor del producto.
B44: Calidad percibida (1-5) | C44: 3 | D44: 1-5
B45: Marca y reputación (1-5) | C45: 3 | D45: 1-5
B46: Diseño y estética (1-5) | C46: 3 | D46: 1-5
B47: Exclusividad / escasez (1-5) | C47: 3 | D47: 1-5
B48: Conveniencia / facilidad (1-5) | C48: 3 | D48: 1-5
B49: Garantías y soporte (1-5) | C49: 3 | D49: 1-5
B50: Puntuación media valor percibido | D50: /5 | E50: =AVERAGE(C44:C49) -> 3
B51: Factor de valor (1.00 – 1.50) | D51: x | E51: =1+(E50-1)*0.5/4 -> 1.25
B53: G. MERCADO Y COMPETENCIA
B54: Precio competidor 1 | C54: 0 | D54: €
B55: Precio competidor 2 | C55: 0 | D55: €
B56: Precio competidor 3 | C56: 0 | D56: €
B57: Elasticidad precio (1=rígida / 5=muy elástica) | C57: 3 | D57: 1-5
B58: Segmento (1=Económico / 2=Medio / 3=Premium) | C58: 2 | D58: 1-3
B59: Media precios mercado | D59: € | E59: =IFERROR(AVERAGEIF(C54:C56,">0"),0) -> 0
B60: Factor segmento (0.85 – 1.20) | D60: x | E60: =0.85+(E58-1)*0.175 -> 0.675
B62: H. CICLO DE VIDA DEL PRODUCTO
B63: Fase (1=Lanzamiento / 2=Crecimiento / 3=Madurez / 4=Liquidación) | C63: 2 | D63: 1-4
B64: Factor ciclo de vida (0.80 – 1.10) | D64: x | E64: =IF(C63=1,1.1,IF(C63=2,1.05,IF(C63=3,1,0.8))) -> 1.05
B66: I. CANAL DE VENTA
B67: Canal (1=Directo / 2=Distribuid. / 3=Marketplace / 4=Mayorista / 5=Afiliad.) | C67: 1 | D67: 1-5
B68: Comisión / descuento canal (%) | C68: 0 | D68: %
B69: Factor canal | D69: x | E69: =1/(1-C68) -> 1
B71: 📊 RESUMEN DE CÁLCULO
B72: ① PVP base (coste + margen) | D72: € | E72: =E40 -> 0
B73: ② Ajuste por valor percibido | D73: € | E73: =E72*E51 -> 0
B74: ③ Ajuste por segmento | D74: € | E74: =E73*E60 -> 0
B75: ④ Ajuste por ciclo de vida | D75: € | E75: =E74*E64 -> 0
B76: ⑤ PVP sin IVA recomendado | D76: € | E76: =E75*E69 -> 0
B77: ⑥ IVA (desde Portada) | D77: % | E77: ='🏠 Portada'!C10/100 -> 0.21
B78: IVA en € | D78: € | E78: =E76*E77 -> 0
B79: 💰 PVP FINAL AL CLIENTE (con IVA) | E79: =E76+E78 -> 0
B81: Precio mínimo aceptable | D81: € | E81: =IF((1-C37)=0,0,E33/(1-C37)*(1+E77)) -> 0
B82: Diferencia vs. media mercado | D82: € | E82: =IF(E59=0,0,E76+E78-E59) -> 0
B84: 📈 ANÁLISIS DE RENTABILIDAD
B85: Margen bruto real (%) | D85: % | E85: =IF(E76=0,0,(E76-E33)/E76) -> 0
B86: Beneficio neto por unidad (€) | D86: € | E86: =E76-E33 -> 0
B87: Ingresos estimados al mes (€) | D87: € | E87: =C25*(E76+E78) -> 0

Sheet 📊 Resumen
B1: RESUMEN COMPARATIVO DE PRECIOS
B4: Introduce el precio sin IVA de cada pestaña en la columna azul. El IVA se aplica automáticamente.
B6: CATEGORÍA | C6: PRECIO SIN IVA (€) | D6: PRECIO CON IVA (€)
B7: 📚 Formaciones | C7: 0 | D7: =C7*(1+'🏠 Portada'!C10/100) -> 0
B8: 🤝 Consultoría | C8: 0 | D8: =C8*(1+'🏠 Portada'!C10/100) -> 0
B9: ⚙️ Ingeniería | C9: 0 | D9: =C9*(1+'🏠 Portada'!C10/100) -> 0
B10: 📦 Producto | C10: 0 | D10: =C10*(1+'🏠 Portada'!C10/100) -> 0
B12: ℹ️ Copia el precio sin IVA (celda E del precio recomendado) de cada pestaña aquí.
B14: COMPARATIVA RÁPIDA
B15: CATEGORÍA | C15: PRECIO s/IVA | D15: MAYOR PRECIO?
B16: 📚 Formaciones | C16: =C7 -> 0 | D16: =IF(C7=MAX($C$7:$C$10),"✅ Más alto","—") -> ✅ Más alto
B17: 🤝 Consultoría | C17: =C8 -> 0 | D17: =IF(C8=MAX($C$7:$C$10),"✅ Más alto","—") -> ✅ Más alto
B18: ⚙️ Ingeniería | C18: =C9 -> 0 | D18: =IF(C9=MAX($C$7:$C$10),"✅ Más alto","—") -> ✅ Más alto
B19: 📦 Producto | C19: =C10 -> 0 | D19: =IF(C10=MAX($C$7:$C$10),"✅ Más alto","—") -> ✅ Más alto
